[
  {
    "@id": "http://environment.data.gov.uk/flood-monitoring/id/measures/1899TH-level-stage-i-15_min-mASD",
    "datumType": "http://environment.data.gov.uk/flood-monitoring/def/core/datumASD",
    "label": "RIVER THAMES AT DAYS LOCK - level-stage-i-15_min-mASD",
    "latestReading": {
      "@id": "http://environment.data.gov.uk/flood-monitoring/data/readings/1899TH-level-stage-i-15_min-mASD/2024-01-04T00-00-00Z",
      "date": "2024-01-04",
      "dateTime": "2024-01-04T00:00:00Z",
      "measure": "http://environment.data.gov.uk/flood-monitoring/id/measures/1899TH-level-stage-i-15_min-mASD",
      "value": 1.03
    },
    "notation": "1899TH-level-stage-i-15_min-mASD",
    "parameter": "level",
    "parameterName": "Water Level",
    "period": 900,
    "qualifier": "Stage",
    "station": "http://environment.data.gov.uk/flood-monitoring/id/stations/1899TH",
    "stationReference": "1899TH",
    "unit": "http://qudt.org/1.1/vocab/unit#Meter",
    "unitName": "mASD",
    "valueType": "instantaneous"
  },
  {
    "@id": "http://environment.data.gov.uk/flood-monitoring/id/measures/1899TH-level-downstage-i-15_min-mASD",
    "datumType": "http://environment.data.gov.uk/flood-monitoring/def/core/datumASD",
    "label": "RIVER THAMES AT DAYS LOCK - level-downstage-i-15_min-mASD",
    "latestReading": {
      "@id": "http://environment.data.gov.uk/flood-monitoring/data/readings/1899TH-level-downstage-i-15_min-mASD/2024-01-04T00-00-00Z",
      "date": "2024-01-04",
      "dateTime": "2024-01-04T00:00:00Z",
      "measure": "http://environment.data.gov.uk/flood-monitoring/id/measures/1899TH-level-downstage-i-15_min-mASD",
      "value": 4.456
    },
    "notation": "1899TH-level-downstage-i-15_min-mASD",
    "parameter": "level",
    "parameterName": "Water Level",
    "period": 900,
    "qualifier": "Downstream Stage",
    "station": "http://environment.data.gov.uk/flood-monitoring/id/stations/1899TH",
    "stationReference": "1899TH",
    "unit": "http://qudt.org/1.1/vocab/unit#Meter",
    "unitName": "mASD",
    "valueType": "instantaneous"
  },
  {
    "@id": "http://environment.data.gov.uk/flood-monitoring/id/measures/1899TH-level-stage-i-15_min----",
    "label": "RIVER THAMES AT DAYS LOCK - level-stage-i-15_min----",
    "notation": "1899TH-level-stage-i-15_min----",
    "parameter": "level",
    "parameterName": "Water Level",
    "period": 900,
    "qualifier": "Stage",
    "station": "http://environment.data.gov.uk/flood-monitoring/id/stations/1899TH",
    "stationReference": "1899TH",
    "unitName": "---",
    "valueType": "instantaneous"
  },
  {
    "@id": "http://environment.data.gov.uk/flood-monitoring/id/measures/1899TH-level-downstage-i-15_min----",
    "label": "RIVER THAMES AT DAYS LOCK - level-downstage-i-15_min----",
    "notation": "1899TH-level-downstage-i-15_min----",
    "parameter": "level",
    "parameterName": "Water Level",
    "period": 900,
    "qualifier": "Downstream Stage",
    "station": "http://environment.data.gov.uk/flood-monitoring/id/stations/1899TH",
    "stationReference": "1899TH",
    "unitName": "---",
    "valueType": "instantaneous"
  }
]